pGerrit/Access.py
pGerrit/__init__.py
pGerrit/change.py
pGerrit/client.py
pGerrit/exception.py
pGerrit/queryMeta.py
pGerrit/restAPIwrapper.py
pGerrit/utils.py
tests/__init__.py
tests/test.py
pGerrit-0.1.4.dist-info/LICENSE
pGerrit-0.1.4.dist-info/METADATA
pGerrit-0.1.4.dist-info/WHEEL
pGerrit-0.1.4.dist-info/top_level.txt
pGerrit-0.1.4.dist-info/RECORD
