Metadata-Version: 2.1
Name: pGerrit
Version: 0.1.4
Summary: A well designed base on decorator pattern library to access Google Gerrit REST API
Home-page: UNKNOWN
Author: CY
Author-email: 17103513@qq.com
License: UNKNOWN
Project-URL: Source, https://github.com/demonguy/pGerrit
Project-URL: Tracker, https://github.com/demonguy/pGerrit/issues
Platform: UNKNOWN
Classifier: Intended Audience :: Developers
Classifier: License :: OSI Approved :: MIT License
Classifier: Operating System :: OS Independent
Classifier: Programming Language :: Python
Classifier: Programming Language :: Python :: 3.6
Classifier: Programming Language :: Python :: 3.7
Classifier: Programming Language :: Python :: 3.8
Classifier: Programming Language :: Python :: 3.9
Classifier: Programming Language :: Python :: 3.10
Classifier: Programming Language :: Python :: 3.11
Requires-Python: >=3.6
Requires-Dist: requests
Requires-Dist: requests-cache
